pluggy_sdk/__init__.py
pluggy_sdk/api_client.py
pluggy_sdk/api_response.py
pluggy_sdk/configuration.py
pluggy_sdk/exceptions.py
pluggy_sdk/py.typed
pluggy_sdk/rest.py
pluggy_sdk/api/__init__.py
pluggy_sdk/api/account_api.py
pluggy_sdk/api/acquirer_anticipation_api.py
pluggy_sdk/api/acquirer_receivable_api.py
pluggy_sdk/api/acquirer_sale_api.py
pluggy_sdk/api/auth_api.py
pluggy_sdk/api/automatic_pix_api.py
pluggy_sdk/api/benefit_api.py
pluggy_sdk/api/bill_api.py
pluggy_sdk/api/boleto_management_api.py
pluggy_sdk/api/bulk_payment_api.py
pluggy_sdk/api/category_api.py
pluggy_sdk/api/connector_api.py
pluggy_sdk/api/consent_api.py
pluggy_sdk/api/identity_api.py
pluggy_sdk/api/income_report_api.py
pluggy_sdk/api/investment_api.py
pluggy_sdk/api/items_api.py
pluggy_sdk/api/loan_api.py
pluggy_sdk/api/payment_customer_api.py
pluggy_sdk/api/payment_intent_api.py
pluggy_sdk/api/payment_receipts_api.py
pluggy_sdk/api/payment_recipient_api.py
pluggy_sdk/api/payment_request_api.py
pluggy_sdk/api/payment_schedule_api.py
pluggy_sdk/api/payroll_loan_api.py
pluggy_sdk/api/portfolio_yield_api.py
pluggy_sdk/api/smart_account_api.py
pluggy_sdk/api/smart_account_transfer_api.py
pluggy_sdk/api/smart_transfer_api.py
pluggy_sdk/api/transaction_api.py
pluggy_sdk/api/webhook_api.py
pluggy_sdk/models/__init__.py
pluggy_sdk/models/account.py
pluggy_sdk/models/account_statements_list200_response.py
pluggy_sdk/models/account_statements_list200_response_results_inner.py
pluggy_sdk/models/accounts_list200_response.py
pluggy_sdk/models/acquirer_anticipation.py
pluggy_sdk/models/acquirer_anticipation_data.py
pluggy_sdk/models/acquirer_data.py
pluggy_sdk/models/acquirer_receivable.py
pluggy_sdk/models/acquirer_receivable_data.py
pluggy_sdk/models/acquirer_receivable_data_establishment.py
pluggy_sdk/models/acquirer_receivable_destination_account.py
pluggy_sdk/models/acquirer_receivable_related_sale.py
pluggy_sdk/models/acquirer_sale.py
pluggy_sdk/models/acquirer_sale_data.py
pluggy_sdk-1.0.0.post54.dist-info/METADATA
pluggy_sdk-1.0.0.post54.dist-info/WHEEL
pluggy_sdk-1.0.0.post54.dist-info/top_level.txt
pluggy_sdk-1.0.0.post54.dist-info/RECORD
