Metadata-Version: 2.4
Name: pluggy_sdk
Version: 1.0.0.post54
Summary: Pluggy API
Home-page: https://github.com/diraol/pluggy-python
Author: Pluggy
Author-email: Pluggy <hello@pluggy.ai>
License: MIT
Project-URL: Repository, https://github.com/GIT_USER_ID/GIT_REPO_ID
Keywords: OpenAPI,OpenAPI-Generator,Pluggy API
Requires-Python: >=3.9
Requires-Dist: urllib3<3.0.0,>=2.1.0
Requires-Dist: python-dateutil>=2.8.2
Requires-Dist: pydantic>=2
Requires-Dist: typing-extensions>=4.7.1
Dynamic: author
Dynamic: home-page
